{"file":"result.png","frames":{
"res_succ_title":{"x":0,"y":115,"w":450,"h":109,"offX":3,"offY":0,"sourceW":453,"sourceH":109},
"res_back_d":{"x":216,"y":384,"w":102,"h":96,"offX":0,"offY":0,"sourceW":102,"sourceH":96},
"res_back_u":{"x":320,"y":384,"w":102,"h":96,"offX":0,"offY":0,"sourceW":102,"sourceH":96},
"res_fail_title":{"x":0,"y":0,"w":443,"h":113,"offX":3,"offY":0,"sourceW":446,"sourceH":113},
"res_menu_d":{"x":419,"y":226,"w":87,"h":79,"offX":0,"offY":0,"sourceW":87,"sourceH":79},
"res_menu_u":{"x":330,"y":226,"w":87,"h":79,"offX":0,"offY":0,"sourceW":87,"sourceH":79},
"res_next_d":{"x":108,"y":384,"w":106,"h":93,"offX":0,"offY":0,"sourceW":106,"sourceH":93},
"res_next_u":{"x":0,"y":384,"w":106,"h":93,"offX":0,"offY":0,"sourceW":106,"sourceH":93},
"res_star_d":{"x":165,"y":226,"w":163,"h":156,"offX":0,"offY":0,"sourceW":163,"sourceH":156},
"res_star_u":{"x":0,"y":226,"w":163,"h":156,"offX":0,"offY":0,"sourceW":163,"sourceH":156}}}